discord_styled
